py_yt/__init__.py
py_yt/__version__.py
py_yt/extras.py
py_yt/search.py
py_yt/core/__init__.py
py_yt/core/channel.py
py_yt/core/channelsearch.py
py_yt/core/componenthandler.py
py_yt/core/constants.py
py_yt/core/hashtag.py
py_yt/core/playlist.py
py_yt/core/requests.py
py_yt/core/search.py
py_yt/core/suggestions.py
py_yt/core/transcript.py
py_yt/core/video.py
py_yt/handlers/__init__.py
py_yt/handlers/componenthandler.py
py_yt/handlers/requesthandler.py
py_yt_search-0.5.7.dist-info/licenses/LICENSE
py_yt_search-0.5.7.dist-info/METADATA
py_yt_search-0.5.7.dist-info/WHEEL
py_yt_search-0.5.7.dist-info/top_level.txt
py_yt_search-0.5.7.dist-info/RECORD
